[
    {
        "Id": "e5a52318ec1dcee10676ddddc236644ced23c80b7dcfed03d303fcdd0ff0e439",
        "Created": "2023-07-20T02:08:07.274636069Z",
        "Path": "bash",
        "Args": [],
        "State": {
            "Status": "running",
            "Running": true,
            "Paused": false,
            "Restarting": false,
            "OOMKilled": false,
            "Dead": false,
            "Pid": 1208664,
            "ExitCode": 0,
            "Error": "",
            "StartedAt": "2023-07-20T02:08:07.988168446Z",
            "FinishedAt": "0001-01-01T00:00:00Z"
        },
        "Image": "sha256:e97a9027dfd6bbf70ad6a5b0b73dba25f540fc8569e2a8cf2a3e4cfbcf721473",
        "ResolvConfPath": "/var/lib/docker/containers/e5a52318ec1dcee10676ddddc236644ced23c80b7dcfed03d303fcdd0ff0e439/resolv.conf",
        "HostnamePath": "/var/lib/docker/containers/e5a52318ec1dcee10676ddddc236644ced23c80b7dcfed03d303fcdd0ff0e439/hostname",
        "HostsPath": "/var/lib/docker/containers/e5a52318ec1dcee10676ddddc236644ced23c80b7dcfed03d303fcdd0ff0e439/hosts",
        "LogPath": "/var/lib/docker/containers/e5a52318ec1dcee10676ddddc236644ced23c80b7dcfed03d303fcdd0ff0e439/e5a52318ec1dcee10676ddddc236644ced23c80b7dcfed03d303fcdd0ff0e439-json.log",
        "Name": "/jike",
        "RestartCount": 0,
        "Driver": "overlay2",
        "Platform": "linux",
        "MountLabel": "",
        "ProcessLabel": "",
        "AppArmorProfile": "docker-default",
        "ExecIDs": null,
        "HostConfig": {
            "Binds": null,
            "ContainerIDFile": "",
            "LogConfig": {
                "Type": "json-file",
                "Config": {}
            },
            "NetworkMode": "default",
            "PortBindings": {},
            "RestartPolicy": {
                "Name": "no",
                "MaximumRetryCount": 0
            },
            "AutoRemove": true,
            "VolumeDriver": "",
            "VolumesFrom": null,
            "ConsoleSize": [
                36,
                266
            ],
            "CapAdd": null,
            "CapDrop": null,
            "CgroupnsMode": "host",
            "Dns": [],
            "DnsOptions": [],
            "DnsSearch": [],
            "ExtraHosts": null,
            "GroupAdd": null,
            "IpcMode": "private",
            "Cgroup": "",
            "Links": null,
            "OomScoreAdj": 0,
            "PidMode": "",
            "Privileged": false,
            "PublishAllPorts": false,
            "ReadonlyRootfs": false,
            "SecurityOpt": null,
            "UTSMode": "",
            "UsernsMode": "",
            "ShmSize": 67108864,
            "Runtime": "runc",
            "Isolation": "",
            "CpuShares": 0,
            "Memory": 0,
            "NanoCpus": 0,
            "CgroupParent": "",
            "BlkioWeight": 0,
            "BlkioWeightDevice": [],
            "BlkioDeviceReadBps": [],
            "BlkioDeviceWriteBps": [],
            "BlkioDeviceReadIOps": [],
            "BlkioDeviceWriteIOps": [],
            "CpuPeriod": 0,
            "CpuQuota": 0,
            "CpuRealtimePeriod": 0,
            "CpuRealtimeRuntime": 0,
            "CpusetCpus": "",
            "CpusetMems": "",
            "Devices": [],
            "DeviceCgroupRules": null,
            "DeviceRequests": null,
            "MemoryReservation": 0,
            "MemorySwap": 0,
            "MemorySwappiness": null,
            "OomKillDisable": false,
            "PidsLimit": null,
            "Ulimits": null,
            "CpuCount": 0,
            "CpuPercent": 0,
            "IOMaximumIOps": 0,
            "IOMaximumBandwidth": 0,
            "MaskedPaths": [
                "/proc/asound",
                "/proc/acpi",
                "/proc/kcore",
                "/proc/keys",
                "/proc/latency_stats",
                "/proc/timer_list",
                "/proc/timer_stats",
                "/proc/sched_debug",
                "/proc/scsi",
                "/sys/firmware"
            ],
            "ReadonlyPaths": [
                "/proc/bus",
                "/proc/fs",
                "/proc/irq",
                "/proc/sys",
                "/proc/sysrq-trigger"
            ]
        },
        "GraphDriver": {
            "Data": {
                "LowerDir": "/var/lib/docker/overlay2/30e2acac0e154a943157f71b341b5bf41bfc515fe8d8ab175207c9b0b64aa7ee-init/diff:/var/lib/docker/overlay2/jdgfcxhc763s6uph8fxpankcn/diff:/var/lib/docker/overlay2/p6scpswh8i0nueawa10qifmi6/diff:/var/lib/docker/overlay2/i5qd96mj8g7ktq429qtx6ouni/diff:/var/lib/docker/overlay2/nzjsz04yctk37sp1j1q5xrl7k/diff:/var/lib/docker/overlay2/7fpbypao40nnmmyekywouarkf/diff:/var/lib/docker/overlay2/tknfyh2le3lh196lw9b0c9pa0/diff:/var/lib/docker/overlay2/yi2684mu1kfro7mqejgk2te80/diff:/var/lib/docker/overlay2/ib49q6zhd2rxnoqxn9sqjckil/diff:/var/lib/docker/overlay2/llv1kxk8pqpx41qarot5q2s3w/diff:/var/lib/docker/overlay2/qow3hd2q1srvjosa89mzx8y02/diff:/var/lib/docker/overlay2/e2a3710f4d5a0c6b7fe989d38368df9984e581afa8032728e3f2bb4dd70ca363/diff",
                "MergedDir": "/var/lib/docker/overlay2/30e2acac0e154a943157f71b341b5bf41bfc515fe8d8ab175207c9b0b64aa7ee/merged",
                "UpperDir": "/var/lib/docker/overlay2/30e2acac0e154a943157f71b341b5bf41bfc515fe8d8ab175207c9b0b64aa7ee/diff",
                "WorkDir": "/var/lib/docker/overlay2/30e2acac0e154a943157f71b341b5bf41bfc515fe8d8ab175207c9b0b64aa7ee/work"
            },
            "Name": "overlay2"
        },
        "Mounts": [],
        "Config": {
            "Hostname": "e5a52318ec1d",
            "Domainname": "",
            "User": "",
            "AttachStdin": true,
            "AttachStdout": true,
            "AttachStderr": true,
            "Tty": true,
            "OpenStdin": true,
            "StdinOnce": true,
            "Env": [
                "PATH=/usr/local/sbin:/usr/local/bin:/usr/sbin:/usr/bin:/sbin:/bin"
            ],
            "Cmd": [
                "bash"
            ],
            "Image": "ponponon/hbase:2.4.17",
            "Volumes": null,
            "WorkingDir": "/root",
            "Entrypoint": null,
            "OnBuild": null,
            "Labels": {}
        },
        "NetworkSettings": {
            "Bridge": "",
            "SandboxID": "86c83db72ad34ccc74c946e3da616db21155ac7ab14871f7596c3baccd28e81f",
            "HairpinMode": false,
            "LinkLocalIPv6Address": "",
            "LinkLocalIPv6PrefixLen": 0,
            "Ports": {},
            "SandboxKey": "/var/run/docker/netns/86c83db72ad3",
            "SecondaryIPAddresses": null,
            "SecondaryIPv6Addresses": null,
            "EndpointID": "1e67d393a44a07ec370a90a6955eebed2dbd76088ac5d265fe4763b4908ac577",
            "Gateway": "172.17.0.1",
            "GlobalIPv6Address": "",
            "GlobalIPv6PrefixLen": 0,
            "IPAddress": "172.17.0.4",
            "IPPrefixLen": 16,
            "IPv6Gateway": "",
            "MacAddress": "02:42:ac:11:00:04",
            "Networks": {
                "bridge": {
                    "IPAMConfig": null,
                    "Links": null,
                    "Aliases": null,
                    "NetworkID": "aff4cce61e9274f5ad854f84c4df21faf82f9bf76893c3a7bb2bb1c99fc292db",
                    "EndpointID": "1e67d393a44a07ec370a90a6955eebed2dbd76088ac5d265fe4763b4908ac577",
                    "Gateway": "172.17.0.1",
                    "IPAddress": "172.17.0.4",
                    "IPPrefixLen": 16,
                    "IPv6Gateway": "",
                    "GlobalIPv6Address": "",
                    "GlobalIPv6PrefixLen": 0,
                    "MacAddress": "02:42:ac:11:00:04",
                    "DriverOpts": null
                }
            }
        }
    }
]